main.py
bachai_calculator_mcp-1.0.0.dist-info/METADATA
bachai_calculator_mcp-1.0.0.dist-info/WHEEL
bachai_calculator_mcp-1.0.0.dist-info/entry_points.txt
bachai_calculator_mcp-1.0.0.dist-info/top_level.txt
bachai_calculator_mcp-1.0.0.dist-info/RECORD
