Metadata-Version: 2.4
Name: bachai-calculator-mcp
Version: 1.0.0
Summary: Calculator MCP Server - Basic math operations via Model Context Protocol
Home-page: https://github.com/BACH-AI-Tools/calculator-mcp
Author: BACH Studio
Author-email: BACH Studio <contact@bachstudio.com>
License: MIT
Project-URL: Homepage, https://github.com/BACH-AI-Tools/calculator-mcp
Keywords: mcp,calculator,math,arithmetic
Classifier: Programming Language :: Python :: 3
Classifier: License :: OSI Approved :: MIT License
Classifier: Operating System :: OS Independent
Requires-Python: >=3.7
Dynamic: author
Dynamic: home-page
Dynamic: requires-python
